avr/__init__.py
avr/_version.py
avr/cli.py
avr/assets/logo.png
avr/lib/__init__.py
avr/lib/avrdude.py
avr/lib/credentials.py
avr/lib/program.py
avr/lib/report.py
omst_avrtool-2.1.0.dist-info/licenses/LICENSE
omst_avrtool-2.1.0.dist-info/METADATA
omst_avrtool-2.1.0.dist-info/WHEEL
omst_avrtool-2.1.0.dist-info/entry_points.txt
omst_avrtool-2.1.0.dist-info/top_level.txt
omst_avrtool-2.1.0.dist-info/RECORD
