Metadata-Version: 2.4
Name: omst-avrtool
Version: 2.1.0
Summary: AVR programming tool for OceanScan-MST
Author-email: Renato Campos <rcampos@oceanscan-mst.com>
Maintainer-email: OceanScan-MST Team <support@oceanscan-mst.com>
License: Copyright (c) 2018 The Python Packaging Authority
Project-URL: Homepage, https://gitlab.com/omst/omst-factory-tools
Classifier: Development Status :: 4 - Beta
Classifier: Programming Language :: Python :: 3
Classifier: Programming Language :: Python :: 3.8
Classifier: Programming Language :: Python :: 3.9
Classifier: Programming Language :: Python :: 3.10
Classifier: Programming Language :: Python :: 3.11
Classifier: Programming Language :: Python :: 3.12
Classifier: License :: OSI Approved :: MIT License
Classifier: Operating System :: OS Independent
Classifier: Environment :: Console
Classifier: Intended Audience :: Developers
Classifier: Topic :: Software Development :: Embedded Systems
Requires-Python: >=3.8
License-File: LICENSE
Requires-Dist: reportlab>=3.6.0
Requires-Dist: appdirs>=1.4.3
Requires-Dist: secretstore>=0.0.2
Requires-Dist: dbus-python>=1.4.0
Requires-Dist: keyring>=23.0.0
Requires-Dist: pysmb>=1.2.11
Provides-Extra: dev
Requires-Dist: pytest>=7.0.0; extra == "dev"
Requires-Dist: pytest-cov>=4.0.0; extra == "dev"
Requires-Dist: black>=23.0.0; extra == "dev"
Requires-Dist: isort>=5.12.0; extra == "dev"
Requires-Dist: mypy>=1.0.0; extra == "dev"
Requires-Dist: build>=0.10.0; extra == "dev"
Requires-Dist: twine>=4.0.2; extra == "dev"
Requires-Dist: sphinx>=6.0.0; extra == "dev"
Dynamic: license-file
